sqliterunner/__init__.py
sqliterunner-0.1.1.dist-info/LICENSE
sqliterunner-0.1.1.dist-info/METADATA
sqliterunner-0.1.1.dist-info/WHEEL
sqliterunner-0.1.1.dist-info/top_level.txt
sqliterunner-0.1.1.dist-info/RECORD
